kseniaWebsocketLibrary/__init__.py
kseniaWebsocketLibrary/crc.py
kseniaWebsocketLibrary/websocketmanager.py
kseniaWebsocketLibrary/wscall.py
kseniawebsocketlibrary-1.0.5.dist-info/licenses/LICENSE
kseniawebsocketlibrary-1.0.5.dist-info/METADATA
kseniawebsocketlibrary-1.0.5.dist-info/WHEEL
kseniawebsocketlibrary-1.0.5.dist-info/top_level.txt
kseniawebsocketlibrary-1.0.5.dist-info/RECORD
